djmx/__init__.py
djmx-0.1.0.dist-info/WHEEL
djmx-0.1.0.dist-info/METADATA
djmx-0.1.0.dist-info/RECORD
