Metadata-Version: 2.1
Name: djmx
Version: 0.1.0
Summary: 
License: MIT
Author: Tim Kamanin
Author-email: tim@timonweb.com
Requires-Python: >=3.9,<4.0
Classifier: License :: OSI Approved :: MIT License
Classifier: Programming Language :: Python :: 3
Classifier: Programming Language :: Python :: 3.9
Requires-Dist: Django (>=3.2.6,<4.0.0)
